{
  "//": "Optional: stadium name overrides by exact team_name. Seeded with Austria examples.",
  "Austria Vienna": "Viola Park (Generali Arena)",
  "FC Blau-Weiss Linz": "Hofmann Personal Stadion (Linzer Stadion)",
  "Grazer AK 1902": "Merkur Arena",
  "LASK": "Raiffeisen Arena (Linz)",
  "Rapid Vienna": "Allianz Stadion",
  "Red Bull Salzburg": "Red Bull Arena (Wals-Siezenheim)",
  "SCR Altach": "CASHPOINT Arena",
  "SK Sturm Graz": "Merkur Arena",
  "SV Ried": "josko ARENA",
  "TSV Hartberg": "Profertil Arena Hartberg",
  "WSG Tirol": "Tivoli Stadion Tirol",
  "Wolfsberger AC": "Lavanttal-Arena"
}
